unieai_mcp_excel/__init__.py
unieai_mcp_excel/server.py
unieai_mcp_excel-0.1.44.dist-info/licenses/LICENSE
unieai_mcp_excel-0.1.44.dist-info/METADATA
unieai_mcp_excel-0.1.44.dist-info/WHEEL
unieai_mcp_excel-0.1.44.dist-info/entry_points.txt
unieai_mcp_excel-0.1.44.dist-info/top_level.txt
unieai_mcp_excel-0.1.44.dist-info/RECORD
